[{"timestamp":1584550800000,"SnowT1":null,"SnowT2":-11.37,"SnowT3":-16.38,"SnowT4":null,"SnowT5":-8.21,"SnowT6":null,"SnowT7":-28.67,"SnowT8":-36.4,"SnowT9":20.8,"SnowT10":null},{"timestamp":1584554400000,"SnowT1":null,"SnowT2":null,"SnowT3":null,"SnowT4":null,"SnowT5":null,"SnowT6":null,"SnowT7":null,"SnowT8":null,"SnowT9":null,"SnowT10":null},{"timestamp":1584558000000,"SnowT1":null,"SnowT2":null,"SnowT3":null,"SnowT4":null,"SnowT5":null,"SnowT6":null,"SnowT7":null,"SnowT8":null,"SnowT9":null,"SnowT10":null},{"timestamp":1584561600000,"SnowT1":null,"SnowT2":null,"SnowT3":null,"SnowT4":null,"SnowT5":null,"SnowT6":null,"SnowT7":null,"SnowT8":null,"SnowT9":null,"SnowT10":null},{"timestamp":1584565200000,"SnowT1":null,"SnowT2":null,"SnowT3":null,"SnowT4":null,"SnowT5":null,"SnowT6":null,"SnowT7":null,"SnowT8":null,"SnowT9":null,"SnowT10":null},{"timestamp":1584568800000,"SnowT1":null,"SnowT2":null,"SnowT3":null,"SnowT4":null,"SnowT5":null,"SnowT6":null,"SnowT7":null,"SnowT8":null,"SnowT9":null,"SnowT10":null},{"timestamp":1584572400000,"SnowT1":null,"SnowT2":null,"SnowT3":null,"SnowT4":null,"SnowT5":null,"SnowT6":null,"SnowT7":null,"SnowT8":null,"SnowT9":null,"SnowT10":null},{"timestamp":1584576000000,"SnowT1":null,"SnowT2":null,"SnowT3":null,"SnowT4":null,"SnowT5":null,"SnowT6":null,"SnowT7":null,"SnowT8":null,"SnowT9":null,"SnowT10":null},{"timestamp":1584579600000,"SnowT1":null,"SnowT2":null,"SnowT3":null,"SnowT4":null,"SnowT5":null,"SnowT6":null,"SnowT7":null,"SnowT8":null,"SnowT9":null,"SnowT10":null},{"timestamp":1584583200000,"SnowT1":null,"SnowT2":null,"SnowT3":null,"SnowT4":null,"SnowT5":null,"SnowT6":null,"SnowT7":null,"SnowT8":null,"SnowT9":null,"SnowT10":null},{"timestamp":1584586800000,"SnowT1":null,"SnowT2":null,"SnowT3":null,"SnowT4":null,"SnowT5":null,"SnowT6":null,"SnowT7":null,"SnowT8":null,"SnowT9":null,"SnowT10":null},{"timestamp":1584590400000,"SnowT1":null,"SnowT2":null,"SnowT3":null,"SnowT4":null,"SnowT5":null,"SnowT6":null,"SnowT7":null,"SnowT8":null,"SnowT9":null,"SnowT10":null},{"timestamp":1584594000000,"SnowT1":null,"SnowT2":null,"SnowT3":null,"SnowT4":null,"SnowT5":null,"SnowT6":null,"SnowT7":null,"SnowT8":null,"SnowT9":null,"SnowT10":null},{"timestamp":1584597600000,"SnowT1":null,"SnowT2":null,"SnowT3":null,"SnowT4":null,"SnowT5":null,"SnowT6":null,"SnowT7":null,"SnowT8":null,"SnowT9":null,"SnowT10":null},{"timestamp":1584601200000,"SnowT1":null,"SnowT2":null,"SnowT3":null,"SnowT4":null,"SnowT5":null,"SnowT6":null,"SnowT7":null,"SnowT8":null,"SnowT9":null,"SnowT10":null},{"timestamp":1584604800000,"SnowT1":null,"SnowT2":null,"SnowT3":null,"SnowT4":null,"SnowT5":null,"SnowT6":null,"SnowT7":null,"SnowT8":null,"SnowT9":null,"SnowT10":null},{"timestamp":1584608400000,"SnowT1":null,"SnowT2":null,"SnowT3":null,"SnowT4":null,"SnowT5":null,"SnowT6":null,"SnowT7":null,"SnowT8":null,"SnowT9":null,"SnowT10":null},{"timestamp":1584612000000,"SnowT1":null,"SnowT2":null,"SnowT3":null,"SnowT4":null,"SnowT5":null,"SnowT6":null,"SnowT7":null,"SnowT8":null,"SnowT9":null,"SnowT10":null},{"timestamp":1584615600000,"SnowT1":null,"SnowT2":null,"SnowT3":null,"SnowT4":null,"SnowT5":null,"SnowT6":null,"SnowT7":null,"SnowT8":null,"SnowT9":null,"SnowT10":null},{"timestamp":1584619200000,"SnowT1":null,"SnowT2":null,"SnowT3":null,"SnowT4":null,"SnowT5":null,"SnowT6":null,"SnowT7":null,"SnowT8":null,"SnowT9":null,"SnowT10":null},{"timestamp":1584622800000,"SnowT1":null,"SnowT2":null,"SnowT3":null,"SnowT4":null,"SnowT5":null,"SnowT6":null,"SnowT7":null,"SnowT8":null,"SnowT9":null,"SnowT10":null},{"timestamp":1584626400000,"SnowT1":null,"SnowT2":null,"SnowT3":null,"SnowT4":null,"SnowT5":null,"SnowT6":null,"SnowT7":null,"SnowT8":null,"SnowT9":null,"SnowT10":null},{"timestamp":1584630000000,"SnowT1":null,"SnowT2":null,"SnowT3":null,"SnowT4":null,"SnowT5":null,"SnowT6":null,"SnowT7":null,"SnowT8":null,"SnowT9":null,"SnowT10":null},{"timestamp":1584633600000,"SnowT1":null,"SnowT2":null,"SnowT3":null,"SnowT4":null,"SnowT5":null,"SnowT6":null,"SnowT7":null,"SnowT8":null,"SnowT9":null,"SnowT10":null},{"timestamp":1584637200000,"SnowT1":null,"SnowT2":null,"SnowT3":null,"SnowT4":null,"SnowT5":null,"SnowT6":null,"SnowT7":null,"SnowT8":null,"SnowT9":null,"SnowT10":null},{"timestamp":1584640800000,"SnowT1":null,"SnowT2":null,"SnowT3":null,"SnowT4":null,"SnowT5":null,"SnowT6":null,"SnowT7":null,"SnowT8":null,"SnowT9":null,"SnowT10":null},{"timestamp":1584644400000,"SnowT1":null,"SnowT2":null,"SnowT3":null,"SnowT4":null,"SnowT5":null,"SnowT6":null,"SnowT7":null,"SnowT8":null,"SnowT9":null,"SnowT10":null},{"timestamp":1584648000000,"SnowT1":null,"SnowT2":null,"SnowT3":null,"SnowT4":null,"SnowT5":null,"SnowT6":null,"SnowT7":null,"SnowT8":null,"SnowT9":null,"SnowT10":null},{"timestamp":1584651600000,"SnowT1":null,"SnowT2":null,"SnowT3":null,"SnowT4":null,"SnowT5":null,"SnowT6":null,"SnowT7":null,"SnowT8":null,"SnowT9":null,"SnowT10":null},{"timestamp":1584655200000,"SnowT1":null,"SnowT2":null,"SnowT3":null,"SnowT4":null,"SnowT5":null,"SnowT6":null,"SnowT7":null,"SnowT8":null,"SnowT9":null,"SnowT10":null},{"timestamp":1584658800000,"SnowT1":null,"SnowT2":null,"SnowT3":null,"SnowT4":null,"SnowT5":null,"SnowT6":null,"SnowT7":null,"SnowT8":null,"SnowT9":null,"SnowT10":null},{"timestamp":1584662400000,"SnowT1":null,"SnowT2":null,"SnowT3":null,"SnowT4":null,"SnowT5":null,"SnowT6":null,"SnowT7":null,"SnowT8":null,"SnowT9":null,"SnowT10":null},{"timestamp":1584666000000,"SnowT1":null,"SnowT2":null,"SnowT3":null,"SnowT4":null,"SnowT5":null,"SnowT6":null,"SnowT7":null,"SnowT8":null,"SnowT9":null,"SnowT10":null},{"timestamp":1584669600000,"SnowT1":null,"SnowT2":null,"SnowT3":null,"SnowT4":null,"SnowT5":null,"SnowT6":null,"SnowT7":null,"SnowT8":null,"SnowT9":null,"SnowT10":null},{"timestamp":1584673200000,"SnowT1":null,"SnowT2":null,"SnowT3":null,"SnowT4":null,"SnowT5":null,"SnowT6":null,"SnowT7":null,"SnowT8":null,"SnowT9":null,"SnowT10":null},{"timestamp":1584676800000,"SnowT1":null,"SnowT2":null,"SnowT3":null,"SnowT4":null,"SnowT5":null,"SnowT6":null,"SnowT7":null,"SnowT8":null,"SnowT9":null,"SnowT10":null},{"timestamp":1584680400000,"SnowT1":null,"SnowT2":null,"SnowT3":null,"SnowT4":null,"SnowT5":null,"SnowT6":null,"SnowT7":null,"SnowT8":null,"SnowT9":null,"SnowT10":null},{"timestamp":1584684000000,"SnowT1":null,"SnowT2":null,"SnowT3":null,"SnowT4":null,"SnowT5":null,"SnowT6":null,"SnowT7":null,"SnowT8":null,"SnowT9":null,"SnowT10":null},{"timestamp":1584687600000,"SnowT1":null,"SnowT2":null,"SnowT3":null,"SnowT4":null,"SnowT5":null,"SnowT6":null,"SnowT7":null,"SnowT8":null,"SnowT9":null,"SnowT10":null},{"timestamp":1584691200000,"SnowT1":null,"SnowT2":null,"SnowT3":null,"SnowT4":null,"SnowT5":null,"SnowT6":null,"SnowT7":null,"SnowT8":null,"SnowT9":null,"SnowT10":null},{"timestamp":1584694800000,"SnowT1":null,"SnowT2":null,"SnowT3":null,"SnowT4":null,"SnowT5":null,"SnowT6":null,"SnowT7":null,"SnowT8":null,"SnowT9":null,"SnowT10":null},{"timestamp":1584698400000,"SnowT1":null,"SnowT2":null,"SnowT3":null,"SnowT4":null,"SnowT5":null,"SnowT6":null,"SnowT7":null,"SnowT8":null,"SnowT9":null,"SnowT10":null},{"timestamp":1584702000000,"SnowT1":null,"SnowT2":null,"SnowT3":null,"SnowT4":null,"SnowT5":null,"SnowT6":null,"SnowT7":null,"SnowT8":null,"SnowT9":null,"SnowT10":null},{"timestamp":1584705600000,"SnowT1":null,"SnowT2":null,"SnowT3":null,"SnowT4":null,"SnowT5":null,"SnowT6":null,"SnowT7":null,"SnowT8":null,"SnowT9":null,"SnowT10":null},{"timestamp":1584709200000,"SnowT1":null,"SnowT2":null,"SnowT3":null,"SnowT4":null,"SnowT5":null,"SnowT6":null,"SnowT7":null,"SnowT8":null,"SnowT9":null,"SnowT10":null},{"timestamp":1584712800000,"SnowT1":null,"SnowT2":null,"SnowT3":null,"SnowT4":null,"SnowT5":null,"SnowT6":null,"SnowT7":null,"SnowT8":null,"SnowT9":null,"SnowT10":null},{"timestamp":1584716400000,"SnowT1":null,"SnowT2":null,"SnowT3":null,"SnowT4":null,"SnowT5":null,"SnowT6":null,"SnowT7":null,"SnowT8":null,"SnowT9":null,"SnowT10":null},{"timestamp":1584720000000,"SnowT1":null,"SnowT2":null,"SnowT3":null,"SnowT4":null,"SnowT5":null,"SnowT6":null,"SnowT7":null,"SnowT8":null,"SnowT9":null,"SnowT10":null},{"timestamp":1584723600000,"SnowT1":null,"SnowT2":null,"SnowT3":null,"SnowT4":null,"SnowT5":null,"SnowT6":null,"SnowT7":null,"SnowT8":null,"SnowT9":null,"SnowT10":null},{"timestamp":1584727200000,"SnowT1":-2.69,"SnowT2":null,"SnowT3":-1.48,"SnowT4":null,"SnowT5":null,"SnowT6":null,"SnowT7":null,"SnowT8":null,"SnowT9":null,"SnowT10":null},{"timestamp":1584730800000,"SnowT1":null,"SnowT2":null,"SnowT3":-1.99,"SnowT4":null,"SnowT5":null,"SnowT6":null,"SnowT7":null,"SnowT8":null,"SnowT9":null,"SnowT10":null},{"timestamp":1584734400000,"SnowT1":null,"SnowT2":null,"SnowT3":null,"SnowT4":null,"SnowT5":null,"SnowT6":null,"SnowT7":null,"SnowT8":null,"SnowT9":null,"SnowT10":null},{"timestamp":1584738000000,"SnowT1":null,"SnowT2":null,"SnowT3":null,"SnowT4":null,"SnowT5":null,"SnowT6":null,"SnowT7":null,"SnowT8":null,"SnowT9":null,"SnowT10":null},{"timestamp":1584741600000,"SnowT1":null,"SnowT2":null,"SnowT3":null,"SnowT4":null,"SnowT5":null,"SnowT6":null,"SnowT7":null,"SnowT8":null,"SnowT9":null,"SnowT10":null},{"timestamp":1584745200000,"SnowT1":null,"SnowT2":null,"SnowT3":null,"SnowT4":null,"SnowT5":null,"SnowT6":null,"SnowT7":null,"SnowT8":null,"SnowT9":null,"SnowT10":null},{"timestamp":1584748800000,"SnowT1":null,"SnowT2":null,"SnowT3":null,"SnowT4":null,"SnowT5":null,"SnowT6":null,"SnowT7":null,"SnowT8":null,"SnowT9":null,"SnowT10":null},{"timestamp":1584752400000,"SnowT1":null,"SnowT2":null,"SnowT3":null,"SnowT4":null,"SnowT5":null,"SnowT6":null,"SnowT7":null,"SnowT8":null,"SnowT9":null,"SnowT10":null},{"timestamp":1584756000000,"SnowT1":null,"SnowT2":null,"SnowT3":null,"SnowT4":null,"SnowT5":null,"SnowT6":null,"SnowT7":null,"SnowT8":null,"SnowT9":null,"SnowT10":null},{"timestamp":1584759600000,"SnowT1":null,"SnowT2":null,"SnowT3":null,"SnowT4":null,"SnowT5":null,"SnowT6":null,"SnowT7":null,"SnowT8":null,"SnowT9":null,"SnowT10":null},{"timestamp":1584763200000,"SnowT1":null,"SnowT2":null,"SnowT3":null,"SnowT4":null,"SnowT5":null,"SnowT6":null,"SnowT7":null,"SnowT8":null,"SnowT9":null,"SnowT10":null},{"timestamp":1584766800000,"SnowT1":null,"SnowT2":null,"SnowT3":null,"SnowT4":null,"SnowT5":null,"SnowT6":null,"SnowT7":null,"SnowT8":null,"SnowT9":null,"SnowT10":null},{"timestamp":1584770400000,"SnowT1":null,"SnowT2":null,"SnowT3":null,"SnowT4":null,"SnowT5":null,"SnowT6":null,"SnowT7":null,"SnowT8":null,"SnowT9":null,"SnowT10":null},{"timestamp":1584774000000,"SnowT1":null,"SnowT2":null,"SnowT3":null,"SnowT4":null,"SnowT5":null,"SnowT6":null,"SnowT7":null,"SnowT8":null,"SnowT9":null,"SnowT10":null},{"timestamp":1584777600000,"SnowT1":null,"SnowT2":null,"SnowT3":null,"SnowT4":null,"SnowT5":null,"SnowT6":null,"SnowT7":null,"SnowT8":null,"SnowT9":null,"SnowT10":null},{"timestamp":1584781200000,"SnowT1":null,"SnowT2":null,"SnowT3":null,"SnowT4":null,"SnowT5":null,"SnowT6":null,"SnowT7":null,"SnowT8":null,"SnowT9":null,"SnowT10":null},{"timestamp":1584784800000,"SnowT1":null,"SnowT2":null,"SnowT3":null,"SnowT4":null,"SnowT5":null,"SnowT6":null,"SnowT7":null,"SnowT8":null,"SnowT9":null,"SnowT10":null},{"timestamp":1584788400000,"SnowT1":null,"SnowT2":null,"SnowT3":null,"SnowT4":null,"SnowT5":null,"SnowT6":null,"SnowT7":null,"SnowT8":null,"SnowT9":null,"SnowT10":null},{"timestamp":1584792000000,"SnowT1":null,"SnowT2":null,"SnowT3":null,"SnowT4":null,"SnowT5":null,"SnowT6":null,"SnowT7":null,"SnowT8":null,"SnowT9":null,"SnowT10":null},{"timestamp":1584795600000,"SnowT1":null,"SnowT2":null,"SnowT3":null,"SnowT4":null,"SnowT5":null,"SnowT6":null,"SnowT7":null,"SnowT8":null,"SnowT9":null,"SnowT10":null},{"timestamp":1584799200000,"SnowT1":null,"SnowT2":null,"SnowT3":null,"SnowT4":null,"SnowT5":null,"SnowT6":null,"SnowT7":null,"SnowT8":null,"SnowT9":null,"SnowT10":null},{"timestamp":1584802800000,"SnowT1":null,"SnowT2":null,"SnowT3":null,"SnowT4":null,"SnowT5":null,"SnowT6":null,"SnowT7":null,"SnowT8":null,"SnowT9":null,"SnowT10":null},{"timestamp":1584806400000,"SnowT1":null,"SnowT2":null,"SnowT3":null,"SnowT4":null,"SnowT5":null,"SnowT6":null,"SnowT7":null,"SnowT8":null,"SnowT9":null,"SnowT10":null},{"timestamp":1584810000000,"SnowT1":null,"SnowT2":null,"SnowT3":null,"SnowT4":null,"SnowT5":null,"SnowT6":null,"SnowT7":null,"SnowT8":null,"SnowT9":null,"SnowT10":null},{"timestamp":1584813600000,"SnowT1":null,"SnowT2":null,"SnowT3":null,"SnowT4":null,"SnowT5":null,"SnowT6":null,"SnowT7":null,"SnowT8":null,"SnowT9":null,"SnowT10":null},{"timestamp":1584817200000,"SnowT1":null,"SnowT2":null,"SnowT3":null,"SnowT4":null,"SnowT5":null,"SnowT6":null,"SnowT7":null,"SnowT8":null,"SnowT9":null,"SnowT10":null},{"timestamp":1584820800000,"SnowT1":null,"SnowT2":null,"SnowT3":null,"SnowT4":null,"SnowT5":null,"SnowT6":null,"SnowT7":null,"SnowT8":null,"SnowT9":null,"SnowT10":null},{"timestamp":1584824400000,"SnowT1":null,"SnowT2":null,"SnowT3":null,"SnowT4":null,"SnowT5":null,"SnowT6":null,"SnowT7":null,"SnowT8":null,"SnowT9":null,"SnowT10":null},{"timestamp":1584828000000,"SnowT1":null,"SnowT2":null,"SnowT3":null,"SnowT4":null,"SnowT5":null,"SnowT6":null,"SnowT7":null,"SnowT8":null,"SnowT9":null,"SnowT10":null},{"timestamp":1584831600000,"SnowT1":null,"SnowT2":null,"SnowT3":null,"SnowT4":null,"SnowT5":null,"SnowT6":null,"SnowT7":null,"SnowT8":null,"SnowT9":null,"SnowT10":null},{"timestamp":1584835200000,"SnowT1":null,"SnowT2":null,"SnowT3":null,"SnowT4":null,"SnowT5":null,"SnowT6":null,"SnowT7":null,"SnowT8":null,"SnowT9":null,"SnowT10":null},{"timestamp":1584838800000,"SnowT1":null,"SnowT2":null,"SnowT3":null,"SnowT4":null,"SnowT5":null,"SnowT6":null,"SnowT7":null,"SnowT8":null,"SnowT9":null,"SnowT10":null},{"timestamp":1584842400000,"SnowT1":null,"SnowT2":null,"SnowT3":null,"SnowT4":null,"SnowT5":null,"SnowT6":null,"SnowT7":null,"SnowT8":null,"SnowT9":null,"SnowT10":null},{"timestamp":1584846000000,"SnowT1":null,"SnowT2":null,"SnowT3":null,"SnowT4":null,"SnowT5":null,"SnowT6":null,"SnowT7":null,"SnowT8":null,"SnowT9":null,"SnowT10":null},{"timestamp":1584849600000,"SnowT1":null,"SnowT2":null,"SnowT3":null,"SnowT4":null,"SnowT5":null,"SnowT6":null,"SnowT7":null,"SnowT8":null,"SnowT9":null,"SnowT10":null},{"timestamp":1584853200000,"SnowT1":null,"SnowT2":null,"SnowT3":null,"SnowT4":null,"SnowT5":null,"SnowT6":null,"SnowT7":null,"SnowT8":null,"SnowT9":null,"SnowT10":null},{"timestamp":1584856800000,"SnowT1":null,"SnowT2":null,"SnowT3":null,"SnowT4":null,"SnowT5":null,"SnowT6":null,"SnowT7":null,"SnowT8":null,"SnowT9":null,"SnowT10":null},{"timestamp":1584860400000,"SnowT1":null,"SnowT2":null,"SnowT3":null,"SnowT4":null,"SnowT5":null,"SnowT6":null,"SnowT7":null,"SnowT8":null,"SnowT9":null,"SnowT10":null},{"timestamp":1584864000000,"SnowT1":null,"SnowT2":null,"SnowT3":null,"SnowT4":null,"SnowT5":null,"SnowT6":null,"SnowT7":null,"SnowT8":null,"SnowT9":null,"SnowT10":null},{"timestamp":1584867600000,"SnowT1":null,"SnowT2":null,"SnowT3":null,"SnowT4":null,"SnowT5":null,"SnowT6":null,"SnowT7":null,"SnowT8":null,"SnowT9":null,"SnowT10":null},{"timestamp":1584871200000,"SnowT1":null,"SnowT2":null,"SnowT3":null,"SnowT4":null,"SnowT5":null,"SnowT6":null,"SnowT7":null,"SnowT8":null,"SnowT9":null,"SnowT10":null},{"timestamp":1584874800000,"SnowT1":null,"SnowT2":null,"SnowT3":null,"SnowT4":null,"SnowT5":null,"SnowT6":null,"SnowT7":null,"SnowT8":null,"SnowT9":null,"SnowT10":null},{"timestamp":1584878400000,"SnowT1":null,"SnowT2":null,"SnowT3":null,"SnowT4":null,"SnowT5":null,"SnowT6":null,"SnowT7":null,"SnowT8":null,"SnowT9":null,"SnowT10":null},{"timestamp":1584882000000,"SnowT1":null,"SnowT2":null,"SnowT3":null,"SnowT4":null,"SnowT5":null,"SnowT6":null,"SnowT7":null,"SnowT8":null,"SnowT9":null,"SnowT10":null},{"timestamp":1584885600000,"SnowT1":null,"SnowT2":null,"SnowT3":null,"SnowT4":null,"SnowT5":null,"SnowT6":null,"SnowT7":null,"SnowT8":null,"SnowT9":null,"SnowT10":null},{"timestamp":1584889200000,"SnowT1":null,"SnowT2":null,"SnowT3":null,"SnowT4":null,"SnowT5":null,"SnowT6":null,"SnowT7":null,"SnowT8":null,"SnowT9":null,"SnowT10":null},{"timestamp":1584892800000,"SnowT1":null,"SnowT2":null,"SnowT3":null,"SnowT4":null,"SnowT5":null,"SnowT6":null,"SnowT7":null,"SnowT8":null,"SnowT9":null,"SnowT10":null},{"timestamp":1584896400000,"SnowT1":null,"SnowT2":null,"SnowT3":null,"SnowT4":null,"SnowT5":null,"SnowT6":null,"SnowT7":null,"SnowT8":null,"SnowT9":null,"SnowT10":null},{"timestamp":1584900000000,"SnowT1":null,"SnowT2":null,"SnowT3":null,"SnowT4":null,"SnowT5":null,"SnowT6":null,"SnowT7":null,"SnowT8":null,"SnowT9":null,"SnowT10":null},{"timestamp":1584903600000,"SnowT1":null,"SnowT2":null,"SnowT3":null,"SnowT4":null,"SnowT5":null,"SnowT6":null,"SnowT7":null,"SnowT8":null,"SnowT9":null,"SnowT10":null},{"timestamp":1584907200000,"SnowT1":null,"SnowT2":null,"SnowT3":null,"SnowT4":null,"SnowT5":null,"SnowT6":null,"SnowT7":null,"SnowT8":null,"SnowT9":null,"SnowT10":null},{"timestamp":1584910800000,"SnowT1":null,"SnowT2":null,"SnowT3":null,"SnowT4":null,"SnowT5":null,"SnowT6":null,"SnowT7":null,"SnowT8":null,"SnowT9":null,"SnowT10":null},{"timestamp":1584914400000,"SnowT1":null,"SnowT2":null,"SnowT3":null,"SnowT4":null,"SnowT5":null,"SnowT6":null,"SnowT7":null,"SnowT8":null,"SnowT9":null,"SnowT10":null},{"timestamp":1584918000000,"SnowT1":null,"SnowT2":null,"SnowT3":null,"SnowT4":null,"SnowT5":null,"SnowT6":null,"SnowT7":null,"SnowT8":null,"SnowT9":null,"SnowT10":null},{"timestamp":1584921600000,"SnowT1":null,"SnowT2":null,"SnowT3":null,"SnowT4":null,"SnowT5":null,"SnowT6":null,"SnowT7":null,"SnowT8":null,"SnowT9":null,"SnowT10":null},{"timestamp":1584925200000,"SnowT1":null,"SnowT2":null,"SnowT3":null,"SnowT4":null,"SnowT5":null,"SnowT6":null,"SnowT7":null,"SnowT8":null,"SnowT9":null,"SnowT10":null},{"timestamp":1584928800000,"SnowT1":null,"SnowT2":null,"SnowT3":null,"SnowT4":null,"SnowT5":null,"SnowT6":null,"SnowT7":null,"SnowT8":null,"SnowT9":null,"SnowT10":null},{"timestamp":1584932400000,"SnowT1":null,"SnowT2":null,"SnowT3":null,"SnowT4":null,"SnowT5":null,"SnowT6":null,"SnowT7":null,"SnowT8":null,"SnowT9":null,"SnowT10":null},{"timestamp":1584936000000,"SnowT1":null,"SnowT2":null,"SnowT3":null,"SnowT4":null,"SnowT5":null,"SnowT6":null,"SnowT7":null,"SnowT8":null,"SnowT9":null,"SnowT10":null},{"timestamp":1584939600000,"SnowT1":null,"SnowT2":null,"SnowT3":null,"SnowT4":null,"SnowT5":null,"SnowT6":null,"SnowT7":null,"SnowT8":null,"SnowT9":null,"SnowT10":null},{"timestamp":1584943200000,"SnowT1":null,"SnowT2":null,"SnowT3":null,"SnowT4":null,"SnowT5":null,"SnowT6":null,"SnowT7":null,"SnowT8":null,"SnowT9":null,"SnowT10":null},{"timestamp":1584946800000,"SnowT1":null,"SnowT2":null,"SnowT3":null,"SnowT4":null,"SnowT5":null,"SnowT6":null,"SnowT7":null,"SnowT8":null,"SnowT9":null,"SnowT10":null},{"timestamp":1584950400000,"SnowT1":null,"SnowT2":null,"SnowT3":null,"SnowT4":null,"SnowT5":null,"SnowT6":null,"SnowT7":null,"SnowT8":null,"SnowT9":null,"SnowT10":null},{"timestamp":1584954000000,"SnowT1":null,"SnowT2":null,"SnowT3":null,"SnowT4":null,"SnowT5":null,"SnowT6":null,"SnowT7":null,"SnowT8":null,"SnowT9":null,"SnowT10":null},{"timestamp":1584957600000,"SnowT1":null,"SnowT2":null,"SnowT3":null,"SnowT4":null,"SnowT5":null,"SnowT6":null,"SnowT7":null,"SnowT8":null,"SnowT9":null,"SnowT10":null},{"timestamp":1584961200000,"SnowT1":null,"SnowT2":null,"SnowT3":null,"SnowT4":null,"SnowT5":null,"SnowT6":null,"SnowT7":null,"SnowT8":null,"SnowT9":null,"SnowT10":null},{"timestamp":1584964800000,"SnowT1":null,"SnowT2":null,"SnowT3":null,"SnowT4":null,"SnowT5":null,"SnowT6":null,"SnowT7":null,"SnowT8":null,"SnowT9":null,"SnowT10":null},{"timestamp":1584968400000,"SnowT1":null,"SnowT2":null,"SnowT3":null,"SnowT4":null,"SnowT5":null,"SnowT6":null,"SnowT7":null,"SnowT8":null,"SnowT9":null,"SnowT10":null},{"timestamp":1584972000000,"SnowT1":null,"SnowT2":null,"SnowT3":null,"SnowT4":null,"SnowT5":null,"SnowT6":null,"SnowT7":null,"SnowT8":null,"SnowT9":null,"SnowT10":null},{"timestamp":1584975600000,"SnowT1":null,"SnowT2":null,"SnowT3":null,"SnowT4":null,"SnowT5":null,"SnowT6":null,"SnowT7":null,"SnowT8":null,"SnowT9":null,"SnowT10":null},{"timestamp":1584979200000,"SnowT1":null,"SnowT2":null,"SnowT3":null,"SnowT4":null,"SnowT5":null,"SnowT6":null,"SnowT7":null,"SnowT8":null,"SnowT9":null,"SnowT10":null},{"timestamp":1584982800000,"SnowT1":null,"SnowT2":null,"SnowT3":-11.62,"SnowT4":null,"SnowT5":null,"SnowT6":null,"SnowT7":-16.87,"SnowT8":-59.56,"SnowT9":-64.09,"SnowT10":null},{"timestamp":1584986400000,"SnowT1":null,"SnowT2":null,"SnowT3":-12.06,"SnowT4":null,"SnowT5":null,"SnowT6":null,"SnowT7":-16.46,"SnowT8":-59.88,"SnowT9":null,"SnowT10":null},{"timestamp":1584990000000,"SnowT1":null,"SnowT2":null,"SnowT3":null,"SnowT4":null,"SnowT5":null,"SnowT6":null,"SnowT7":null,"SnowT8":null,"SnowT9":null,"SnowT10":null},{"timestamp":1584993600000,"SnowT1":null,"SnowT2":null,"SnowT3":null,"SnowT4":null,"SnowT5":null,"SnowT6":null,"SnowT7":null,"SnowT8":null,"SnowT9":null,"SnowT10":null},{"timestamp":1584997200000,"SnowT1":null,"SnowT2":null,"SnowT3":null,"SnowT4":null,"SnowT5":null,"SnowT6":null,"SnowT7":null,"SnowT8":null,"SnowT9":null,"SnowT10":null},{"timestamp":1585000800000,"SnowT1":null,"SnowT2":null,"SnowT3":null,"SnowT4":null,"SnowT5":null,"SnowT6":null,"SnowT7":null,"SnowT8":null,"SnowT9":null,"SnowT10":null},{"timestamp":1585004400000,"SnowT1":null,"SnowT2":null,"SnowT3":null,"SnowT4":null,"SnowT5":null,"SnowT6":null,"SnowT7":null,"SnowT8":null,"SnowT9":null,"SnowT10":null},{"timestamp":1585008000000,"SnowT1":null,"SnowT2":null,"SnowT3":null,"SnowT4":null,"SnowT5":null,"SnowT6":null,"SnowT7":null,"SnowT8":null,"SnowT9":null,"SnowT10":null},{"timestamp":1585011600000,"SnowT1":null,"SnowT2":null,"SnowT3":null,"SnowT4":null,"SnowT5":null,"SnowT6":null,"SnowT7":null,"SnowT8":null,"SnowT9":null,"SnowT10":null},{"timestamp":1585015200000,"SnowT1":null,"SnowT2":null,"SnowT3":null,"SnowT4":null,"SnowT5":null,"SnowT6":null,"SnowT7":null,"SnowT8":null,"SnowT9":null,"SnowT10":null},{"timestamp":1585018800000,"SnowT1":null,"SnowT2":null,"SnowT3":null,"SnowT4":null,"SnowT5":null,"SnowT6":null,"SnowT7":null,"SnowT8":null,"SnowT9":null,"SnowT10":null},{"timestamp":1585022400000,"SnowT1":null,"SnowT2":null,"SnowT3":null,"SnowT4":null,"SnowT5":null,"SnowT6":null,"SnowT7":null,"SnowT8":null,"SnowT9":null,"SnowT10":null},{"timestamp":1585026000000,"SnowT1":null,"SnowT2":null,"SnowT3":null,"SnowT4":null,"SnowT5":null,"SnowT6":null,"SnowT7":null,"SnowT8":null,"SnowT9":null,"SnowT10":null},{"timestamp":1585029600000,"SnowT1":null,"SnowT2":null,"SnowT3":null,"SnowT4":null,"SnowT5":null,"SnowT6":null,"SnowT7":null,"SnowT8":null,"SnowT9":null,"SnowT10":null},{"timestamp":1585033200000,"SnowT1":null,"SnowT2":null,"SnowT3":null,"SnowT4":null,"SnowT5":null,"SnowT6":null,"SnowT7":null,"SnowT8":null,"SnowT9":null,"SnowT10":null},{"timestamp":1585036800000,"SnowT1":null,"SnowT2":null,"SnowT3":null,"SnowT4":null,"SnowT5":null,"SnowT6":null,"SnowT7":null,"SnowT8":null,"SnowT9":null,"SnowT10":null},{"timestamp":1585040400000,"SnowT1":null,"SnowT2":null,"SnowT3":null,"SnowT4":null,"SnowT5":null,"SnowT6":null,"SnowT7":null,"SnowT8":null,"SnowT9":null,"SnowT10":null},{"timestamp":1585044000000,"SnowT1":null,"SnowT2":null,"SnowT3":null,"SnowT4":null,"SnowT5":null,"SnowT6":null,"SnowT7":null,"SnowT8":null,"SnowT9":null,"SnowT10":null},{"timestamp":1585047600000,"SnowT1":null,"SnowT2":null,"SnowT3":null,"SnowT4":null,"SnowT5":null,"SnowT6":null,"SnowT7":null,"SnowT8":null,"SnowT9":null,"SnowT10":null},{"timestamp":1585051200000,"SnowT1":null,"SnowT2":null,"SnowT3":null,"SnowT4":null,"SnowT5":null,"SnowT6":null,"SnowT7":null,"SnowT8":null,"SnowT9":null,"SnowT10":null},{"timestamp":1585054800000,"SnowT1":null,"SnowT2":null,"SnowT3":null,"SnowT4":null,"SnowT5":null,"SnowT6":null,"SnowT7":null,"SnowT8":null,"SnowT9":null,"SnowT10":null},{"timestamp":1585058400000,"SnowT1":null,"SnowT2":null,"SnowT3":null,"SnowT4":null,"SnowT5":null,"SnowT6":null,"SnowT7":null,"SnowT8":null,"SnowT9":null,"SnowT10":null},{"timestamp":1585062000000,"SnowT1":null,"SnowT2":null,"SnowT3":null,"SnowT4":null,"SnowT5":null,"SnowT6":null,"SnowT7":null,"SnowT8":null,"SnowT9":null,"SnowT10":null},{"timestamp":1585065600000,"SnowT1":null,"SnowT2":null,"SnowT3":-13.96,"SnowT4":null,"SnowT5":null,"SnowT6":null,"SnowT7":-22.36,"SnowT8":-53.97,"SnowT9":-63.86,"SnowT10":null},{"timestamp":1585069200000,"SnowT1":null,"SnowT2":null,"SnowT3":-12.57,"SnowT4":null,"SnowT5":null,"SnowT6":null,"SnowT7":-17.68,"SnowT8":-60.86,"SnowT9":-63.86,"SnowT10":null},{"timestamp":1585072800000,"SnowT1":null,"SnowT2":null,"SnowT3":-12.5,"SnowT4":null,"SnowT5":null,"SnowT6":null,"SnowT7":-13.91,"SnowT8":null,"SnowT9":-64.13,"SnowT10":null},{"timestamp":1585076400000,"SnowT1":null,"SnowT2":-4.54,"SnowT3":-13.57,"SnowT4":null,"SnowT5":null,"SnowT6":null,"SnowT7":-14.72,"SnowT8":null,"SnowT9":-63.77,"SnowT10":null},{"timestamp":1585080000000,"SnowT1":null,"SnowT2":-8.27,"SnowT3":-15.01,"SnowT4":null,"SnowT5":null,"SnowT6":null,"SnowT7":-16.32,"SnowT8":-59.81,"SnowT9":-63.56,"SnowT10":null},{"timestamp":1585083600000,"SnowT1":null,"SnowT2":null,"SnowT3":null,"SnowT4":null,"SnowT5":null,"SnowT6":null,"SnowT7":null,"SnowT8":null,"SnowT9":null,"SnowT10":null},{"timestamp":1585087200000,"SnowT1":null,"SnowT2":null,"SnowT3":null,"SnowT4":null,"SnowT5":null,"SnowT6":null,"SnowT7":null,"SnowT8":null,"SnowT9":null,"SnowT10":null},{"timestamp":1585090800000,"SnowT1":null,"SnowT2":null,"SnowT3":null,"SnowT4":null,"SnowT5":null,"SnowT6":null,"SnowT7":null,"SnowT8":null,"SnowT9":null,"SnowT10":null},{"timestamp":1585094400000,"SnowT1":null,"SnowT2":null,"SnowT3":null,"SnowT4":null,"SnowT5":null,"SnowT6":null,"SnowT7":null,"SnowT8":null,"SnowT9":null,"SnowT10":null},{"timestamp":1585098000000,"SnowT1":null,"SnowT2":null,"SnowT3":null,"SnowT4":null,"SnowT5":null,"SnowT6":null,"SnowT7":null,"SnowT8":null,"SnowT9":null,"SnowT10":null},{"timestamp":1585101600000,"SnowT1":null,"SnowT2":null,"SnowT3":null,"SnowT4":null,"SnowT5":null,"SnowT6":null,"SnowT7":null,"SnowT8":null,"SnowT9":null,"SnowT10":null},{"timestamp":1585105200000,"SnowT1":null,"SnowT2":null,"SnowT3":null,"SnowT4":null,"SnowT5":null,"SnowT6":null,"SnowT7":null,"SnowT8":null,"SnowT9":null,"SnowT10":null},{"timestamp":1585108800000,"SnowT1":null,"SnowT2":null,"SnowT3":null,"SnowT4":null,"SnowT5":null,"SnowT6":null,"SnowT7":null,"SnowT8":null,"SnowT9":null,"SnowT10":null},{"timestamp":1585112400000,"SnowT1":null,"SnowT2":null,"SnowT3":null,"SnowT4":null,"SnowT5":null,"SnowT6":null,"SnowT7":null,"SnowT8":null,"SnowT9":null,"SnowT10":null},{"timestamp":1585116000000,"SnowT1":null,"SnowT2":null,"SnowT3":null,"SnowT4":null,"SnowT5":null,"SnowT6":null,"SnowT7":null,"SnowT8":null,"SnowT9":null,"SnowT10":null},{"timestamp":1585119600000,"SnowT1":null,"SnowT2":null,"SnowT3":null,"SnowT4":null,"SnowT5":null,"SnowT6":null,"SnowT7":null,"SnowT8":null,"SnowT9":null,"SnowT10":null},{"timestamp":1585123200000,"SnowT1":null,"SnowT2":null,"SnowT3":null,"SnowT4":null,"SnowT5":null,"SnowT6":null,"SnowT7":null,"SnowT8":null,"SnowT9":null,"SnowT10":null},{"timestamp":1585126800000,"SnowT1":null,"SnowT2":null,"SnowT3":null,"SnowT4":null,"SnowT5":null,"SnowT6":null,"SnowT7":null,"SnowT8":null,"SnowT9":null,"SnowT10":null},{"timestamp":1585130400000,"SnowT1":null,"SnowT2":null,"SnowT3":null,"SnowT4":null,"SnowT5":null,"SnowT6":null,"SnowT7":null,"SnowT8":null,"SnowT9":null,"SnowT10":null},{"timestamp":1585134000000,"SnowT1":null,"SnowT2":null,"SnowT3":null,"SnowT4":null,"SnowT5":null,"SnowT6":null,"SnowT7":null,"SnowT8":null,"SnowT9":null,"SnowT10":null},{"timestamp":1585137600000,"SnowT1":null,"SnowT2":null,"SnowT3":-19.24,"SnowT4":null,"SnowT5":-11.35,"SnowT6":null,"SnowT7":-30.52,"SnowT8":-44.03,"SnowT9":-64.77,"SnowT10":-14.45},{"timestamp":1585141200000,"SnowT1":null,"SnowT2":null,"SnowT3":-16.38,"SnowT4":null,"SnowT5":-4.38,"SnowT6":null,"SnowT7":-26.92,"SnowT8":-47.53,"SnowT9":-63.81,"SnowT10":null},{"timestamp":1585144800000,"SnowT1":null,"SnowT2":null,"SnowT3":-14.28,"SnowT4":null,"SnowT5":null,"SnowT6":null,"SnowT7":-23.22,"SnowT8":-52.28,"SnowT9":-63.28,"SnowT10":null},{"timestamp":1585148400000,"SnowT1":null,"SnowT2":null,"SnowT3":-12.14,"SnowT4":null,"SnowT5":null,"SnowT6":null,"SnowT7":-19.27,"SnowT8":-58.23,"SnowT9":-63.08,"SnowT10":null},{"timestamp":1585152000000,"SnowT1":null,"SnowT2":null,"SnowT3":-10.46,"SnowT4":null,"SnowT5":null,"SnowT6":null,"SnowT7":-15.42,"SnowT8":null,"SnowT9":null,"SnowT10":null},{"timestamp":1585155600000,"SnowT1":null,"SnowT2":null,"SnowT3":-9.34,"SnowT4":null,"SnowT5":null,"SnowT6":null,"SnowT7":-12.13,"SnowT8":null,"SnowT9":null,"SnowT10":null},{"timestamp":1585159200000,"SnowT1":null,"SnowT2":null,"SnowT3":-9.66,"SnowT4":null,"SnowT5":null,"SnowT6":null,"SnowT7":-11.35,"SnowT8":null,"SnowT9":null,"SnowT10":null},{"timestamp":1585162800000,"SnowT1":null,"SnowT2":null,"SnowT3":-9.37,"SnowT4":null,"SnowT5":null,"SnowT6":null,"SnowT7":-11.08,"SnowT8":null,"SnowT9":null,"SnowT10":null},{"timestamp":1585166400000,"SnowT1":null,"SnowT2":-4.87,"SnowT3":-10.88,"SnowT4":null,"SnowT5":null,"SnowT6":null,"SnowT7":-9.44,"SnowT8":null,"SnowT9":null,"SnowT10":null}]