[{"timestamp":1584810000000,"SWin":164.2,"SWout":292.0,"NetRad":-9.6},{"timestamp":1584813600000,"SWin":95.4,"SWout":270.0,"NetRad":-3.36},{"timestamp":1584817200000,"SWin":55.4,"SWout":212.6,"NetRad":-13.68},{"timestamp":1584820800000,"SWin":33.8,"SWout":105.4,"NetRad":-16.4},{"timestamp":1584824400000,"SWin":14.6,"SWout":44.6,"NetRad":-16.96},{"timestamp":1584828000000,"SWin":1.6,"SWout":3.0,"NetRad":-13.12},{"timestamp":1584831600000,"SWin":0.0,"SWout":0.0,"NetRad":-10.96},{"timestamp":1584835200000,"SWin":0.0,"SWout":0.0,"NetRad":-13.12},{"timestamp":1584838800000,"SWin":0.0,"SWout":0.0,"NetRad":-12.64},{"timestamp":1584842400000,"SWin":0.0,"SWout":0.0,"NetRad":-13.84},{"timestamp":1584846000000,"SWin":0.0,"SWout":0.0,"NetRad":-16.88},{"timestamp":1584849600000,"SWin":0.0,"SWout":0.0,"NetRad":-18.0},{"timestamp":1584853200000,"SWin":0.0,"SWout":0.0,"NetRad":-12.4},{"timestamp":1584856800000,"SWin":0.0,"SWout":0.0,"NetRad":-9.28},{"timestamp":1584860400000,"SWin":0.0,"SWout":0.0,"NetRad":-10.96},{"timestamp":1584864000000,"SWin":0.2,"SWout":0.2,"NetRad":-13.92},{"timestamp":1584867600000,"SWin":9.2,"SWout":18.0,"NetRad":-18.24},{"timestamp":1584871200000,"SWin":54.6,"SWout":88.2,"NetRad":-21.84},{"timestamp":1584874800000,"SWin":105.2,"SWout":152.4,"NetRad":-19.6},{"timestamp":1584878400000,"SWin":145.2,"SWout":226.6,"NetRad":2.88},{"timestamp":1584882000000,"SWin":183.2,"SWout":296.2,"NetRad":39.04},{"timestamp":1584885600000,"SWin":217.2,"SWout":346.4,"NetRad":66.08},{"timestamp":1584889200000,"SWin":242.2,"SWout":370.4,"NetRad":80.4},{"timestamp":1584892800000,"SWin":233.2,"SWout":365.2,"NetRad":77.84},{"timestamp":1584896400000,"SWin":159.6,"SWout":336.8,"NetRad":62.32},{"timestamp":1584900000000,"SWin":72.2,"SWout":286.6,"NetRad":47.76},{"timestamp":1584903600000,"SWin":50.2,"SWout":181.0,"NetRad":19.28},{"timestamp":1584907200000,"SWin":43.0,"SWout":113.8,"NetRad":-0.24},{"timestamp":1584910800000,"SWin":16.0,"SWout":30.8,"NetRad":-11.84},{"timestamp":1584914400000,"SWin":2.4,"SWout":4.0,"NetRad":-14.16},{"timestamp":1584918000000,"SWin":0.0,"SWout":0.0,"NetRad":-10.64},{"timestamp":1584921600000,"SWin":0.0,"SWout":0.0,"NetRad":-12.8},{"timestamp":1584925200000,"SWin":0.0,"SWout":0.0,"NetRad":-14.08},{"timestamp":1584928800000,"SWin":0.0,"SWout":0.0,"NetRad":-13.76},{"timestamp":1584932400000,"SWin":0.0,"SWout":0.0,"NetRad":-12.8},{"timestamp":1584936000000,"SWin":0.0,"SWout":0.0,"NetRad":-11.84},{"timestamp":1584939600000,"SWin":0.0,"SWout":0.0,"NetRad":-9.76},{"timestamp":1584943200000,"SWin":0.0,"SWout":0.0,"NetRad":-4.8},{"timestamp":1584946800000,"SWin":0.0,"SWout":0.0,"NetRad":-8.4},{"timestamp":1584950400000,"SWin":0.0,"SWout":0.2,"NetRad":-6.72},{"timestamp":1584954000000,"SWin":3.8,"SWout":8.8,"NetRad":-10.0},{"timestamp":1584957600000,"SWin":35.4,"SWout":78.6,"NetRad":-19.52},{"timestamp":1584961200000,"SWin":62.6,"SWout":135.4,"NetRad":-28.48},{"timestamp":1584964800000,"SWin":92.0,"SWout":226.6,"NetRad":-22.8},{"timestamp":1584968400000,"SWin":127.0,"SWout":296.0,"NetRad":-12.96},{"timestamp":1584972000000,"SWin":155.2,"SWout":339.6,"NetRad":14.24},{"timestamp":1584975600000,"SWin":166.6,"SWout":343.8,"NetRad":21.44},{"timestamp":1584979200000,"SWin":163.6,"SWout":348.0,"NetRad":21.2},{"timestamp":1584982800000,"SWin":117.2,"SWout":325.6,"NetRad":34.16},{"timestamp":1584986400000,"SWin":71.4,"SWout":270.4,"NetRad":15.92},{"timestamp":1584990000000,"SWin":64.0,"SWout":182.6,"NetRad":-8.64},{"timestamp":1584993600000,"SWin":38.8,"SWout":131.4,"NetRad":-13.44},{"timestamp":1584997200000,"SWin":20.4,"SWout":71.0,"NetRad":-16.32},{"timestamp":1585000800000,"SWin":2.8,"SWout":8.8,"NetRad":-8.16},{"timestamp":1585004400000,"SWin":0.0,"SWout":0.2,"NetRad":-9.76},{"timestamp":1585008000000,"SWin":0.0,"SWout":0.0,"NetRad":-12.16},{"timestamp":1585011600000,"SWin":0.0,"SWout":0.0,"NetRad":-7.68},{"timestamp":1585015200000,"SWin":0.0,"SWout":0.0,"NetRad":-3.52},{"timestamp":1585018800000,"SWin":0.0,"SWout":0.0,"NetRad":-7.92},{"timestamp":1585022400000,"SWin":0.0,"SWout":0.0,"NetRad":-21.04},{"timestamp":1585026000000,"SWin":0.0,"SWout":0.0,"NetRad":-14.4},{"timestamp":1585029600000,"SWin":0.0,"SWout":0.0,"NetRad":-21.12},{"timestamp":1585033200000,"SWin":0.0,"SWout":0.0,"NetRad":-1.68},{"timestamp":1585036800000,"SWin":0.2,"SWout":0.4,"NetRad":-5.36},{"timestamp":1585040400000,"SWin":10.6,"SWout":21.2,"NetRad":-9.76},{"timestamp":1585044000000,"SWin":55.4,"SWout":97.6,"NetRad":-27.12},{"timestamp":1585047600000,"SWin":88.8,"SWout":160.2,"NetRad":-53.52},{"timestamp":1585051200000,"SWin":104.8,"SWout":233.6,"NetRad":-52.72},{"timestamp":1585054800000,"SWin":125.0,"SWout":301.6,"NetRad":-17.52},{"timestamp":1585058400000,"SWin":166.8,"SWout":351.2,"NetRad":6.8},{"timestamp":1585062000000,"SWin":199.4,"SWout":373.6,"NetRad":42.16},{"timestamp":1585065600000,"SWin":176.0,"SWout":369.8,"NetRad":54.64},{"timestamp":1585069200000,"SWin":103.8,"SWout":343.4,"NetRad":40.64},{"timestamp":1585072800000,"SWin":60.0,"SWout":295.8,"NetRad":23.04},{"timestamp":1585076400000,"SWin":44.8,"SWout":230.8,"NetRad":12.32},{"timestamp":1585080000000,"SWin":34.4,"SWout":152.2,"NetRad":-3.12},{"timestamp":1585083600000,"SWin":23.6,"SWout":76.6,"NetRad":-2.8},{"timestamp":1585087200000,"SWin":3.4,"SWout":8.6,"NetRad":-0.4},{"timestamp":1585090800000,"SWin":0.0,"SWout":0.0,"NetRad":0.64},{"timestamp":1585094400000,"SWin":0.0,"SWout":0.0,"NetRad":0.56},{"timestamp":1585098000000,"SWin":0.0,"SWout":0.0,"NetRad":-1.2},{"timestamp":1585101600000,"SWin":0.0,"SWout":0.0,"NetRad":-0.48},{"timestamp":1585105200000,"SWin":0.0,"SWout":0.0,"NetRad":-0.48},{"timestamp":1585108800000,"SWin":0.0,"SWout":0.0,"NetRad":-0.4},{"timestamp":1585112400000,"SWin":0.0,"SWout":0.0,"NetRad":-1.12},{"timestamp":1585116000000,"SWin":0.2,"SWout":0.0,"NetRad":-2.48},{"timestamp":1585119600000,"SWin":0.0,"SWout":0.0,"NetRad":-2.16},{"timestamp":1585123200000,"SWin":0.4,"SWout":0.8,"NetRad":-2.0},{"timestamp":1585126800000,"SWin":10.4,"SWout":22.6,"NetRad":-6.08},{"timestamp":1585130400000,"SWin":51.2,"SWout":98.6,"NetRad":-23.04},{"timestamp":1585134000000,"SWin":84.2,"SWout":162.2,"NetRad":-46.64},{"timestamp":1585137600000,"SWin":99.6,"SWout":231.8,"NetRad":-72.16},{"timestamp":1585141200000,"SWin":117.6,"SWout":292.6,"NetRad":-58.4},{"timestamp":1585144800000,"SWin":152.8,"SWout":332.8,"NetRad":-20.56},{"timestamp":1585148400000,"SWin":164.8,"SWout":332.2,"NetRad":-23.44},{"timestamp":1585152000000,"SWin":162.4,"SWout":363.6,"NetRad":-6.0},{"timestamp":1585155600000,"SWin":110.0,"SWout":341.2,"NetRad":9.28},{"timestamp":1585159200000,"SWin":71.0,"SWout":263.8,"NetRad":12.96},{"timestamp":1585162800000,"SWin":62.4,"SWout":187.6,"NetRad":-3.04},{"timestamp":1585166400000,"SWin":40.8,"SWout":99.4,"NetRad":-3.76},{"timestamp":1585170000000,"SWin":15.8,"SWout":33.2,"NetRad":-5.2},{"timestamp":1585173600000,"SWin":2.8,"SWout":5.6,"NetRad":0.64},{"timestamp":1585177200000,"SWin":0.0,"SWout":0.0,"NetRad":0.4},{"timestamp":1585180800000,"SWin":0.0,"SWout":0.0,"NetRad":-3.76},{"timestamp":1585184400000,"SWin":0.0,"SWout":0.0,"NetRad":-3.12},{"timestamp":1585188000000,"SWin":0.0,"SWout":0.0,"NetRad":-2.72},{"timestamp":1585191600000,"SWin":0.0,"SWout":0.0,"NetRad":-0.88},{"timestamp":1585195200000,"SWin":0.0,"SWout":0.0,"NetRad":-2.56},{"timestamp":1585198800000,"SWin":0.0,"SWout":0.0,"NetRad":4.24},{"timestamp":1585202400000,"SWin":0.0,"SWout":0.0,"NetRad":-6.8},{"timestamp":1585206000000,"SWin":0.0,"SWout":0.0,"NetRad":-5.68},{"timestamp":1585209600000,"SWin":0.4,"SWout":0.8,"NetRad":-2.48},{"timestamp":1585213200000,"SWin":6.8,"SWout":14.0,"NetRad":-7.92}]